Metadata-Version: 2.1
Name: dj-paddle
Version: 0.1.2
Summary: Django + Paddle Made Easy
Home-page: https://github.com/dj-paddle/dj-paddle/
Author: Florian Purchess
Author-email: florian.purchess@googlemail.com
License: UNKNOWN
Download-URL: https://github.com/dj-paddle/dj-paddle/tarball/master
Keywords: django,paddle,payments
Platform: UNKNOWN
Classifier: Development Status :: 3 - Alpha
Classifier: Environment :: Web Environment
Classifier: Intended Audience :: Developers
Classifier: License :: OSI Approved :: MIT License
Classifier: Topic :: Office/Business :: Financial
Classifier: Programming Language :: Python :: 3
Classifier: Programming Language :: Python :: 3.5
Classifier: Programming Language :: Python :: 3.6
Classifier: Programming Language :: Python :: 3.7
Classifier: Programming Language :: Python :: 3.8
Classifier: Framework :: Django
Classifier: Framework :: Django :: 2.1
Classifier: Framework :: Django :: 2.2
Classifier: Framework :: Django :: 3.0
Requires-Dist: django (>=2.1)
Requires-Dist: pycryptodome (>=3.9.4)
Requires-Dist: phpserialize (>=1.3)
Requires-Dist: paddle-client (>=0.6.0)
